{
  "end_date": "19671130",
  "results": [
    {
      "abstract": null,
      "headline": {
        "kicker": "1",
        "main": "Space and Missiles; A Giant Step Toward the Moon"
      },
      "keywords": [],
      "print_page": "209",
      "pub_date": "1967-11-12T00:00:00Z",
      "web_url": "http://select.nytimes.com/gst/abstract.html?res=9C05E3DD123FE53BBC4A52DFB767838C679EDE",
      "news_desk": null,
      "snippet": "Flying men to the moon, only a dream for centuries, ranks as the foremost engineering challenge of our time and a distinct possibility in this decade.  ",
      "type_of_material": "Article",
      "blog": [],
      "section_name": null,
      "document_type": "article",
      "byline": null,
      "subsection_name": null,
      "multimedia": [],
      "_id": "4fc4656345c1498b0d99c3c0",
      "source": "The New York Times",
      "word_count": 1283,
      "lead_paragraph": "Flying men to the moon, only a dream for centuries, ranks as the foremost engineering challenge of our time and a distinct possibility in this decade."
    },
    {
      "abstract": "Jane's All the World's Aircraft (pub), holding war between US and USSR unthinkable, suggests 2 nations enter 'mutual survival pact' against nuclear potential of Communist China and France",
      "headline": {"main": "U.S.-SOVIET ACCORD FOR SURVIVAL URGED"},
      "keywords": [
        {
          "name": "subject",
          "value": "JANE'S ALL THE WORLD'S AIRCRAFT (PUB)"
        },
        {
          "name": "subject",
          "value": "ASTRONAUTICS"
        },
        {
          "name": "subject",
          "value": "USSR PROJECTS"
        },
        {
          "name": "subject",
          "value": "SOYUZ 1"
        },
        {
          "name": "subject",
          "value": "INTERNATIONAL RELATIONS"
        },
        {
          "name": "subject",
          "value": "COMMUNIST-WESTERN CONFRONTATION"
        }
      ],
      "print_page": "13",
      "pub_date": "1967-11-29T00:00:00Z",
      "web_url": "http://select.nytimes.com/gst/abstract.html?res=9E00EEDA173CE637A2575AC2A9679D946691D6CF",
      "news_desk": null,
      "snippet": "LONDON, Nov. 28 (UPI)-- An authoritative publication on military power said today that the United States and the Soviet Union should enter a \"mutual survival pact\" against the nuclear potential of Communist China and France.",
      "type_of_material": "Article",
      "blog": [],
      "section_name": null,
      "document_type": "article",
      "byline": null,
      "subsection_name": null,
      "multimedia": [],
      "_id": "4fc4672c45c1498b0d9a41eb",
      "source": "The New York Times",
      "word_count": 172,
      "lead_paragraph": "LONDON, Nov. 28 (UPI)-- An authoritative publication on military power said today that the United States and the Soviet Union should enter a \"mutual survival pact\" against the nuclear potential of Communist China and France."
    }
  ],
  "begin_date": "19671101",
  "query_string": "http://api.nytimes.com/svc/search/v2/articlesearch.json?api-key=4f706a6d31e2514b86ba30e7e6f61ebf:6:69057235&q=\"Cosmonaut\"&begin_date=19671101&end_date=19671130&sort=oldest&page=1",
  "total_results": 2,
  "search_term": "\"Cosmonaut\""
}