{
  "end_date": "20130831",
  "results": [
    {
      "abstract": null,
      "headline": {
        "print_headline": "Today in History",
        "main": "Today in History"
      },
      "keywords": [],
      "print_page": null,
      "pub_date": "2013-08-06T00:00:05Z",
      "web_url": "http://www.nytimes.com/aponline/2013/08/06/us/ap-history.html",
      "news_desk": "None",
      "snippet": "Today is Tuesday, Aug. 6, the 218th day of 2013. There are 147 days left in the year.",
      "type_of_material": "News",
      "blog": [],
      "section_name": "U.S.",
      "document_type": "article",
      "byline": {
        "organization": "THE ASSOCIATED PRESS",
        "person": [],
        "original": "By THE ASSOCIATED PRESS"
      },
      "subsection_name": null,
      "multimedia": [],
      "_id": "520074ff79881007d5901ab9",
      "source": "AP",
      "word_count": "801",
      "lead_paragraph": "Today is Tuesday, Aug. 6, the 218th day of 2013. There are 147 days left in the year."
    },
    {
      "abstract": null,
      "headline": {
        "print_headline": "Identical Twin U.S. Astronauts to Serve as Research Subjects",
        "main": "Identical Twin U.S. Astronauts to Serve as Research Subjects"
      },
      "keywords": [],
      "print_page": null,
      "pub_date": "2013-08-09T13:36:56Z",
      "web_url": "http://www.nytimes.com/reuters/2013/08/09/us/09reuters-space-astronauts.html",
      "news_desk": "None",
      "snippet": "NASA's only identical twin astronauts are planning to serve as guinea pigs for studies investigating the genetic impacts of long-duration spaceflight.",
      "type_of_material": "News",
      "blog": [],
      "section_name": "U.S.",
      "document_type": "article",
      "byline": {
        "organization": "REUTERS",
        "person": [],
        "original": "By REUTERS"
      },
      "subsection_name": null,
      "multimedia": [],
      "_id": "5205294c79881007d59026d1",
      "source": "Reuters",
      "word_count": "386",
      "lead_paragraph": "NASA's only identical twin astronauts are planning to serve as guinea pigs for studies investigating the genetic impacts of long-duration spaceflight."
    },
    {
      "abstract": null,
      "headline": {
        "print_headline": "Today in History",
        "main": "Today in History"
      },
      "keywords": [],
      "print_page": null,
      "pub_date": "2013-08-10T00:00:04Z",
      "web_url": "http://www.nytimes.com/aponline/2013/08/10/us/ap-history.html",
      "news_desk": "None",
      "snippet": "Today is Saturday, Aug. 10, the 222nd day of 2013. There are 143 days left in the year.",
      "type_of_material": "News",
      "blog": [],
      "section_name": "U.S.",
      "document_type": "article",
      "byline": {
        "organization": "THE ASSOCIATED PRESS",
        "person": [],
        "original": "By THE ASSOCIATED PRESS"
      },
      "subsection_name": null,
      "multimedia": [],
      "_id": "5205baf079881007d5902875",
      "source": "AP",
      "word_count": "768",
      "lead_paragraph": "Today is Saturday, Aug. 10, the 222nd day of 2013. There are 143 days left in the year."
    },
    {
      "abstract": null,
      "headline": {
        "print_headline": "Today in History",
        "main": "Today in History"
      },
      "keywords": [],
      "print_page": null,
      "pub_date": "2013-08-11T00:00:50Z",
      "web_url": "http://www.nytimes.com/aponline/2013/08/11/us/ap-history.html",
      "news_desk": "None",
      "snippet": "Today is Sunday, Aug. 11, the 223rd day of 2013. There are 142 days left in the year.",
      "type_of_material": "News",
      "blog": [],
      "section_name": "U.S.",
      "document_type": "article",
      "byline": {
        "organization": "THE ASSOCIATED PRESS",
        "person": [],
        "original": "By THE ASSOCIATED PRESS"
      },
      "subsection_name": null,
      "multimedia": [],
      "_id": "52070d1479881007d5902a0a",
      "source": "AP",
      "word_count": "749",
      "lead_paragraph": "Today is Sunday, Aug. 11, the 223rd day of 2013. There are 142 days left in the year."
    },
    {
      "abstract": null,
      "headline": {
        "print_headline": "Today in History",
        "main": "Today in History"
      },
      "keywords": [],
      "print_page": null,
      "pub_date": "2013-08-12T00:00:15Z",
      "web_url": "http://www.nytimes.com/aponline/2013/08/12/us/ap-history.html",
      "news_desk": "None",
      "snippet": "Today is Monday, Aug. 12, the 224th day of 2013. There are 141 days left in the year.",
      "type_of_material": "News",
      "blog": [],
      "section_name": "U.S.",
      "document_type": "article",
      "byline": {
        "organization": "THE ASSOCIATED PRESS",
        "person": [],
        "original": "By THE ASSOCIATED PRESS"
      },
      "subsection_name": null,
      "multimedia": [],
      "_id": "52085e9b79881007d5902c1e",
      "source": "AP",
      "word_count": "645",
      "lead_paragraph": "Today is Monday, Aug. 12, the 224th day of 2013. There are 141 days left in the year."
    },
    {
      "abstract": null,
      "headline": {
        "print_headline": "Today in History",
        "main": "Today in History"
      },
      "keywords": [],
      "print_page": null,
      "pub_date": "2013-08-19T00:00:51Z",
      "web_url": "http://www.nytimes.com/aponline/2013/08/19/us/ap-history.html",
      "news_desk": "None",
      "snippet": "Today is Monday, Aug. 19, the 231st day of 2013. There are 134 days left in the year.",
      "type_of_material": "News",
      "blog": [],
      "section_name": "U.S.",
      "document_type": "article",
      "byline": {
        "organization": "THE ASSOCIATED PRESS",
        "person": [],
        "original": "By THE ASSOCIATED PRESS"
      },
      "subsection_name": null,
      "multimedia": [],
      "_id": "5211989b79881007d590412f",
      "source": "AP",
      "word_count": "896",
      "lead_paragraph": "Today is Monday, Aug. 19, the 231st day of 2013. There are 134 days left in the year."
    }
  ],
  "begin_date": "20130801",
  "query_string": "http://api.nytimes.com/svc/search/v2/articlesearch.json?api-key=4f706a6d31e2514b86ba30e7e6f61ebf:6:69057235&q=\"Cosmonaut\"&begin_date=20130801&end_date=20130831&sort=oldest&page=1",
  "total_results": 6,
  "search_term": "\"Cosmonaut\""
}